audio_to_midi/__init__.py
audio_to_midi/converter.py
audio_to_midi/main.py
audio_to_midi/midi_writer.py
audio_to_midi/notes.py
audio_to_midi/progress_bar.py
audio_to_midi-2020.7.dist-info/COPYING
audio_to_midi-2020.7.dist-info/METADATA
audio_to_midi-2020.7.dist-info/WHEEL
audio_to_midi-2020.7.dist-info/entry_points.txt
audio_to_midi-2020.7.dist-info/top_level.txt
audio_to_midi-2020.7.dist-info/RECORD
