Metadata-Version: 2.1
Name: audio-to-midi
Version: 2020.7
Summary: Convert audio to multichannel MIDI.
Home-page: https://github.com/NFJones/audio-to-midi
Author: Neil F Jones
License: UNKNOWN
Keywords: audio midi conversion
Platform: UNKNOWN
Classifier: License :: OSI Approved :: MIT License
Classifier: Programming Language :: Python :: 3
Requires-Python: >=3.5, <4
Requires-Dist: cffi (==1.12.3)
Requires-Dist: Cython (==0.29.7)
Requires-Dist: numpy (==1.16.3)
Requires-Dist: pycparser (==2.19)
Requires-Dist: SoundFile (==0.10.2)
Requires-Dist: progressbar2 (==3.50.0)
Requires-Dist: python3-midi (==0.2.5)
